LICENSE
MANIFEST.in
README.md
setup.py
ieml/__init__.py
ieml/commons.py
ieml/constants.py
ieml/default_config.conf
ieml/exceptions.py
ieml/tools.py
ieml.egg-info/PKG-INFO
ieml.egg-info/SOURCES.txt
ieml.egg-info/dependency_links.txt
ieml.egg-info/not-zip-safe
ieml.egg-info/requires.txt
ieml.egg-info/top_level.txt
ieml/dictionary/__init__.py
ieml/dictionary/dictionary.py
ieml/dictionary/distance.py
ieml/dictionary/relations.py
ieml/dictionary/table.py
ieml/dictionary/terms.py
ieml/dictionary/tools.py
ieml/dictionary/version.py
ieml/dictionary/script/__init__.py
ieml/dictionary/script/operator.py
ieml/dictionary/script/script.py
ieml/dictionary/script/tools.py
ieml/dictionary/script/parser/__init__.py
ieml/dictionary/script/parser/lexer.py
ieml/dictionary/script/parser/parser.py
ieml/distance/__init__.py
ieml/distance/order.py
ieml/distance/projection.py
ieml/distance/sort.py
ieml/grammar/__init__.py
ieml/grammar/distance.py
ieml/grammar/fact.py
ieml/grammar/template.py
ieml/grammar/text.py
ieml/grammar/theory.py
ieml/grammar/tools.py
ieml/grammar/topic.py
ieml/grammar/tree_graph.py
ieml/grammar/usl.py
ieml/grammar/word.py
ieml/grammar/parser/__init__.py
ieml/grammar/parser/lexer.py
ieml/grammar/parser/parser.py
ieml/grammar/paths/__init__.py
ieml/grammar/paths/constants.py
ieml/grammar/paths/paths.py
ieml/grammar/paths/tools.py
ieml/grammar/paths/parser/__init__.py
ieml/grammar/paths/parser/lexer.py
ieml/grammar/paths/parser/parser.py