Metadata-Version: 1.1
Name: ieml
Version: 1.0.1
Summary: Python implementation of the artificial natural language IEML
Home-page: https://github.com/IEMLdev/ieml
Author: Louis van Beurden
Author-email: louis.vanbeurden@gmail.com
License: GPLv3
Keywords: ieml semantic-representation syntax semantic-relations semantic-distance
Platform: UNKNOWN
Classifier: License :: OSI Approved :: GNU General Public License v3 (GPLv3)
Classifier: Programming Language :: Python :: 3.5
Classifier: Topic :: Text Processing :: Linguistic
Classifier: Topic :: Text Processing :: Indexing
